LICENSE
astboom/__init__.py
astboom/__main__.py
astboom/cli.py
astboom/visualizers/__init__.py
astboom/visualizers/ast.py
astboom/visualizers/base.py
astboom/visualizers/cst.py
astboom/visualizers/lib_cst.py
astboom/visualizers/st.py
astboom/visualizers/utils.py
astboom-0.4.2.dist-info/entry_points.txt
astboom-0.4.2.dist-info/LICENSE
astboom-0.4.2.dist-info/WHEEL
astboom-0.4.2.dist-info/METADATA
astboom-0.4.2.dist-info/RECORD
