Metadata-Version: 2.1
Name: astboom
Version: 0.4.2
Summary: Visualize Python AST in console.
Home-page: https://github.com/lensvol/astboom
License: MIT
Keywords: ast
Author: Kirill Borisov
Author-email: lensvol@gmail.com
Requires-Python: >=3.6,<4.0
Classifier: Development Status :: 3 - Alpha
Classifier: Environment :: Console
Classifier: Intended Audience :: Developers
Classifier: License :: OSI Approved :: MIT License
Classifier: Operating System :: OS Independent
Classifier: Programming Language :: Python
Classifier: Programming Language :: Python :: 3
Classifier: Programming Language :: Python :: 3.6
Classifier: Programming Language :: Python :: 3.7
Classifier: Programming Language :: Python :: 3.8
Classifier: Topic :: Software Development
Classifier: Topic :: Software Development :: Quality Assurance
Classifier: Topic :: Utilities
Requires-Dist: asciitree (>=0.3.3,<0.4.0)
Requires-Dist: click (>=7.0,<8.0)
Requires-Dist: libcst (>=0.3.1,<0.4.0)
Requires-Dist: pyyaml (>=5.3,<6.0)
Project-URL: Repository, https://github.com/lensvol/astboom
